chlengmo/__init__.py
chlengmo/exceptions.py
chlengmo/main.py
chlengmo-0.0.4.dist-info/LICENSE
chlengmo-0.0.4.dist-info/METADATA
chlengmo-0.0.4.dist-info/WHEEL
chlengmo-0.0.4.dist-info/top_level.txt
chlengmo-0.0.4.dist-info/RECORD
