Metadata-Version: 2.1
Name: chlengmo
Version: 0.0.4
Summary: A fast Character-Level N-Gram Model
Home-page: https://github.com/VictorDavis/chlengmo
Author: Victor Davis
Author-email: victor.davis@toptal.com
Classifier: Programming Language :: Python :: 3
Classifier: License :: OSI Approved :: MIT License
Classifier: Operating System :: OS Independent
Requires-Python: >=3.6
License-File: LICENSE
